wdpass/__init__.py
wdpass/version.py
wdpass-0.1.0.dist-info/LICENSE
wdpass-0.1.0.dist-info/METADATA
wdpass-0.1.0.dist-info/WHEEL
wdpass-0.1.0.dist-info/entry_points.txt
wdpass-0.1.0.dist-info/top_level.txt
wdpass-0.1.0.dist-info/RECORD
